{
  "slide": 15,
  "title": "中国硫酸镍价格再次升水金属镍",
  "charts": [
    {
      "chartPath": "ppt/charts/chart19.xml",
      "chartType": "lineChart",
      "title": null,
      "workbook": "ppt/embeddings/Microsoft_Excel_Worksheet18.xlsx",
      "categoryLabels": [
        "2025-09-29",
        "2025-09-26",
        "2025-09-25",
        "2025-09-24",
        "2025-09-23",
        "2025-09-22",
        "2025-09-19",
        "2025-09-18",
        "2025-09-17",
        "2025-09-16",
        "2025-09-15",
        "2025-09-12",
        "2025-09-11",
        "2025-09-10",
        "2025-09-09",
        "2025-09-08",
        "2025-09-05",
        "2025-09-04",
        "2025-09-03",
        "2025-09-02",
        "2025-09-01",
        "2025-08-29",
        "2025-08-28",
        "2025-08-27",
        "2025-08-26",
        "2025-08-25",
        "2025-08-22",
        "2025-08-21",
        "2025-08-20",
        "2025-08-19",
        "2025-08-18",
        "2025-08-15",
        "2025-08-14",
        "2025-08-13",
        "2025-08-12",
        "2025-08-11",
        "2025-08-08",
        "2025-08-07",
        "2025-08-06",
        "2025-08-05",
        "2025-08-04",
        "2025-08-01",
        "2025-07-31",
        "2025-07-30",
        "2025-07-29",
        "2025-07-28",
        "2025-07-25",
        "2025-07-24",
        "2025-07-23",
        "2025-07-22",
        "2025-07-21",
        "2025-07-18",
        "2025-07-17",
        "2025-07-16",
        "2025-07-15",
        "2025-07-14",
        "2025-07-11",
        "2025-07-10",
        "2025-07-09",
        "2025-07-08",
        "2025-07-07",
        "2025-07-04",
        "2025-07-03",
        "2025-07-02",
        "2025-07-01",
        "2025-06-30",
        "2025-06-27",
        "2025-06-26",
        "2025-06-25",
        "2025-06-24",
        "2025-06-23",
        "2025-06-20",
        "2025-06-19",
        "2025-06-18",
        "2025-06-17",
        "2025-06-16",
        "2025-06-13",
        "2025-06-12",
        "2025-06-11",
        "2025-06-10",
        "2025-06-09",
        "2025-06-06",
        "2025-06-05",
        "2025-06-04",
        "2025-06-03",
        "2025-05-30",
        "2025-05-29",
        "2025-05-28",
        "2025-05-27",
        "2025-05-26",
        "2025-05-23",
        "2025-05-22",
        "2025-05-21",
        "2025-05-20",
        "2025-05-19",
        "2025-05-16",
        "2025-05-15",
        "2025-05-14",
        "2025-05-13",
        "2025-05-12",
        "2025-05-09",
        "2025-05-08",
        "2025-05-07",
        "2025-05-06",
        "2025-05-05",
        "2025-05-02",
        "2025-05-01",
        "2025-04-30",
        "2025-04-29",
        "2025-04-28",
        "2025-04-25",
        "2025-04-24",
        "2025-04-23",
        "2025-04-22",
        "2025-04-21",
        "2025-04-18",
        "2025-04-17",
        "2025-04-16",
        "2025-04-15",
        "2025-04-14",
        "2025-04-11",
        "2025-04-10",
        "2025-04-09",
        "2025-04-08",
        "2025-04-07",
        "2025-04-03",
        "2025-04-02",
        "2025-04-01",
        "2025-03-31",
        "2025-03-28",
        "2025-03-27",
        "2025-03-26",
        "2025-03-25",
        "2025-03-24",
        "2025-03-21",
        "2025-03-20",
        "2025-03-19",
        "2025-03-18",
        "2025-03-17",
        "2025-03-14",
        "2025-03-13",
        "2025-03-12",
        "2025-03-11",
        "2025-03-10",
        "2025-03-07",
        "2025-03-06",
        "2025-03-05",
        "2025-03-04",
        "2025-03-03",
        "2025-02-28",
        "2025-02-27",
        "2025-02-26",
        "2025-02-25",
        "2025-02-24",
        "2025-02-21",
        "2025-02-20",
        "2025-02-19",
        "2025-02-18",
        "2025-02-17",
        "2025-02-14",
        "2025-02-13",
        "2025-02-12",
        "2025-02-11",
        "2025-02-10",
        "2025-02-07",
        "2025-02-06",
        "2025-02-05",
        "2025-01-27",
        "2025-01-24",
        "2025-01-23",
        "2025-01-22",
        "2025-01-21",
        "2025-01-20",
        "2025-01-17",
        "2025-01-16",
        "2025-01-15",
        "2025-01-14",
        "2025-01-13",
        "2025-01-10",
        "2025-01-09",
        "2025-01-08",
        "2025-01-07",
        "2025-01-06",
        "2025-01-03",
        "2025-01-02",
        "2024-12-31",
        "2024-12-30",
        "2024-12-27",
        "2024-12-26",
        "2024-12-25",
        "2024-12-24",
        "2024-12-23",
        "2024-12-20",
        "2024-12-19",
        "2024-12-18",
        "2024-12-17",
        "2024-12-16",
        "2024-12-13",
        "2024-12-12",
        "2024-12-11",
        "2024-12-10",
        "2024-12-09",
        "2024-12-06",
        "2024-12-05",
        "2024-12-04",
        "2024-12-03",
        "2024-12-02",
        "2024-11-29",
        "2024-11-28",
        "2024-11-27",
        "2024-11-26",
        "2024-11-25",
        "2024-11-22",
        "2024-11-21",
        "2024-11-20",
        "2024-11-19",
        "2024-11-18",
        "2024-11-15",
        "2024-11-14",
        "2024-11-13",
        "2024-11-12",
        "2024-11-11",
        "2024-11-08",
        "2024-11-07",
        "2024-11-06",
        "2024-11-05",
        "2024-11-04",
        "2024-11-01",
        "2024-10-31",
        "2024-10-30",
        "2024-10-29",
        "2024-10-28",
        "2024-10-25",
        "2024-10-24",
        "2024-10-23",
        "2024-10-22",
        "2024-10-21",
        "2024-10-18",
        "2024-10-17",
        "2024-10-16",
        "2024-10-15",
        "2024-10-14",
        "2024-10-11",
        "2024-10-10",
        "2024-10-09",
        "2024-10-08",
        "2024-09-30",
        "2024-09-27",
        "2024-09-26",
        "2024-09-25",
        "2024-09-24",
        "2024-09-23",
        "2024-09-20",
        "2024-09-19",
        "2024-09-18",
        "2024-09-13",
        "2024-09-12",
        "2024-09-11",
        "2024-09-10",
        "2024-09-09",
        "2024-09-06",
        "2024-09-05",
        "2024-09-04",
        "2024-09-03",
        "2024-09-02",
        "2024-08-30",
        "2024-08-29",
        "2024-08-28",
        "2024-08-27",
        "2024-08-26",
        "2024-08-23",
        "2024-08-22",
        "2024-08-21",
        "2024-08-20",
        "2024-08-19",
        "2024-08-16",
        "2024-08-15",
        "2024-08-14",
        "2024-08-13",
        "2024-08-12",
        "2024-08-09",
        "2024-08-08",
        "2024-08-07",
        "2024-08-06",
        "2024-08-05",
        "2024-08-02",
        "2024-08-01",
        "2024-07-31",
        "2024-07-30",
        "2024-07-29",
        "2024-07-26",
        "2024-07-25",
        "2024-07-24",
        "2024-07-23",
        "2024-07-22",
        "2024-07-19",
        "2024-07-18",
        "2024-07-17",
        "2024-07-16",
        "2024-07-15",
        "2024-07-12",
        "2024-07-11",
        "2024-07-10",
        "2024-07-09",
        "2024-07-08",
        "2024-07-05",
        "2024-07-04",
        "2024-07-03",
        "2024-07-02",
        "2024-07-01",
        "2024-06-28",
        "2024-06-27",
        "2024-06-26",
        "2024-06-25",
        "2024-06-24",
        "2024-06-21",
        "2024-06-20",
        "2024-06-19",
        "2024-06-18",
        "2024-06-17",
        "2024-06-14",
        "2024-06-13",
        "2024-06-12",
        "2024-06-11",
        "2024-06-07",
        "2024-06-06",
        "2024-06-05",
        "2024-06-04",
        "2024-06-03",
        "2024-05-31",
        "2024-05-30",
        "2024-05-29",
        "2024-05-28",
        "2024-05-27",
        "2024-05-24",
        "2024-05-23",
        "2024-05-22",
        "2024-05-21",
        "2024-05-20",
        "2024-05-17",
        "2024-05-16",
        "2024-05-15",
        "2024-05-14",
        "2024-05-13",
        "2024-05-10",
        "2024-05-09",
        "2024-05-08",
        "2024-05-07",
        "2024-05-06",
        "2024-04-30",
        "2024-04-29",
        "2024-04-26",
        "2024-04-25",
        "2024-04-24",
        "2024-04-23",
        "2024-04-22",
        "2024-04-19",
        "2024-04-18",
        "2024-04-17",
        "2024-04-16",
        "2024-04-15",
        "2024-04-12",
        "2024-04-11",
        "2024-04-10",
        "2024-04-09",
        "2024-04-08",
        "2024-04-03",
        "2024-04-02",
        "2024-04-01",
        "2024-03-29",
        "2024-03-28",
        "2024-03-27",
        "2024-03-26",
        "2024-03-25",
        "2024-03-22",
        "2024-03-21",
        "2024-03-20",
        "2024-03-19",
        "2024-03-18",
        "2024-03-15",
        "2024-03-14",
        "2024-03-13",
        "2024-03-12",
        "2024-03-11",
        "2024-03-08",
        "2024-03-07",
        "2024-03-06",
        "2024-03-05",
        "2024-03-04",
        "2024-03-01",
        "2024-02-29",
        "2024-02-28",
        "2024-02-27",
        "2024-02-26",
        "2024-02-23",
        "2024-02-22",
        "2024-02-21",
        "2024-02-20",
        "2024-02-19",
        "2024-02-08",
        "2024-02-07",
        "2024-02-06",
        "2024-02-05",
        "2024-02-02",
        "2024-02-01",
        "2024-01-31",
        "2024-01-30",
        "2024-01-29",
        "2024-01-26",
        "2024-01-25",
        "2024-01-24",
        "2024-01-23",
        "2024-01-22",
        "2024-01-19",
        "2024-01-18",
        "2024-01-17",
        "2024-01-16",
        "2024-01-15",
        "2024-01-12",
        "2024-01-11",
        "2024-01-10",
        "2024-01-09",
        "2024-01-08",
        "2024-01-05",
        "2024-01-04",
        "2024-01-03",
        "2024-01-02"
      ],
      "categoryRange": "Sheet6!$B$4:$B$430",
      "series": [
        {
          "name": "镍计价系数",
          "values": [
            85.5,
            85.5,
            85.5,
            85.5,
            85.5,
            85.5,
            85.5,
            85.5,
            85.5,
            85.5,
            85.5,
            85.5,
            85.5,
            85.5,
            85.5,
            85.5,
            85.5,
            85.5,
            85.5,
            85.5,
            85.5,
            85.5,
            85.5,
            85.5,
            85.5,
            85.5,
            85.5,
            85.0,
            85.0,
            85.0,
            85.0,
            84.5,
            84.5,
            84.5,
            84.5,
            84.5,
            84.25,
            84.25,
            84.25,
            84.25,
            83.75,
            83.75,
            83.75,
            83.75,
            83.75,
            83.75,
            83.75,
            83.75,
            83.75,
            83.75,
            83.75,
            83.75,
            83.75,
            83.75,
            83.75,
            83.75,
            83.75,
            83.75,
            83.75,
            83.75,
            83.75,
            83.75,
            83.75,
            83.75,
            83.75,
            83.75,
            83.75,
            83.75,
            83.75,
            83.75,
            83.75,
            83.75,
            83.75,
            83.75,
            83.75,
            83.75,
            83.75,
            83.75,
            83.75,
            83.75,
            83.75,
            83.75,
            83.75,
            83.75,
            83.75,
            83.75,
            83.75,
            83.75,
            83.75,
            83.75,
            83.75,
            83.75,
            83.75,
            84.5,
            84.5,
            84.5,
            84.5,
            84.5,
            84.5,
            84.5,
            84.5,
            84.5,
            84.5,
            84.5,
            84.5,
            84.5,
            84.5,
            84.5,
            84.5,
            84.5,
            84.5,
            84.5,
            84.5,
            83.75,
            83.75,
            83.75,
            83.75,
            83.75,
            83.75,
            83.75,
            83.25,
            83.25,
            83.25,
            83.25,
            83.25,
            83.25,
            82.75,
            82.25,
            82.25,
            82.25,
            82.25,
            82.25,
            81.75,
            81.25,
            81.25,
            81.25,
            81.25,
            81.25,
            81.25,
            81.25,
            81.25,
            80.75,
            80.75,
            80.75,
            80.75,
            80.25,
            80.25,
            80.25,
            80.25,
            79.75,
            78.75,
            78.75,
            78.75,
            78.75,
            78.75,
            78.75,
            78.75,
            78.75,
            78.75,
            78.75,
            78.75,
            78.75,
            78.75,
            78.75,
            78.75,
            78.75,
            78.75,
            78.75,
            78.75,
            78.75,
            78.75,
            78.75,
            78.75,
            78.5,
            78.5,
            78.5,
            78.5,
            78.5,
            78.5,
            78.5,
            78.5,
            78.5,
            78.5,
            78.5,
            78.5,
            78.5,
            78.5,
            78.5,
            78.5,
            78.5,
            78.5,
            78.5,
            78.5,
            78.5,
            79.5,
            79.75,
            79.75,
            79.75,
            79.75,
            79.75,
            79.75,
            79.75,
            81.25,
            81.25,
            81.25,
            81.25,
            81.25,
            81.25,
            81.25,
            81.25,
            81.25,
            81.25,
            81.25,
            81.75,
            81.75,
            81.75,
            81.75,
            81.75,
            82.25,
            82.25,
            82.25,
            82.25,
            82.25,
            82.25,
            82.25,
            82.25,
            82.25,
            82.25,
            82.25,
            82.25,
            82.25,
            82.75,
            82.75,
            82.75,
            82.75,
            82.75,
            82.75,
            82.75,
            82.75,
            82.75,
            82.75,
            82.75,
            82.75,
            82.75,
            82.5,
            82.5,
            82.5,
            82.5,
            82.5,
            82.5,
            82.5,
            82.5,
            82.5,
            82.5,
            82.5,
            82.5,
            82.75,
            82.75,
            82.75,
            82.75,
            82.75,
            82.75,
            82.75,
            82.75,
            82.75,
            82.75,
            82.75,
            82.5,
            80.5,
            80.5,
            80.5,
            80.5,
            80.5,
            80.5,
            80.5,
            80.75,
            80.75,
            80.75,
            80.75,
            80.75,
            81.25,
            81.25,
            81.25,
            81.25,
            81.25,
            81.25,
            81.5,
            82.5,
            82.5,
            82.5,
            82.5,
            82.5,
            82.5,
            82.5,
            82.5,
            82.5,
            82.5,
            82.5,
            82.5,
            82.5,
            82.5,
            82.5,
            82.5,
            82.5,
            82.5,
            82.5,
            82.5,
            82.5,
            82.5,
            82.5,
            82.5,
            82.5,
            82.5,
            83.0,
            83.0,
            83.5,
            83.5,
            83.5,
            83.5,
            83.75,
            84.5,
            84.5,
            84.5,
            84.5,
            83.75,
            83.75,
            83.75,
            83.75,
            83.75,
            83.5,
            83.5,
            83.5,
            83.5,
            83.5,
            83.5,
            83.5,
            82.5,
            82.5,
            82.5,
            82.5,
            82.5,
            82.5,
            82.5,
            82.5,
            82.5,
            82.5,
            82.5,
            82.5,
            82.5,
            82.5,
            82.5,
            82.5,
            82.5,
            82.5,
            82.5,
            82.5,
            82.5,
            82.5,
            82.5,
            82.5,
            82.5,
            82.5,
            82.5,
            82.5,
            82.5,
            82.5,
            82.5,
            82.5,
            82.5,
            82.5,
            82.5,
            82.5,
            82.5,
            82.5,
            82.5,
            82.5,
            82.5,
            81.5,
            81.5,
            81.5,
            81.5,
            81.5,
            81.5,
            81.5,
            81.5,
            81.5,
            81.5,
            81.5,
            81.5,
            81.5,
            81.5,
            80.5,
            80.5,
            80.5,
            79.5,
            79.5,
            79.5,
            79.0,
            79.0,
            77.5,
            77.5,
            77.5,
            77.5,
            77.5,
            77.5,
            77.5,
            77.5,
            77.5,
            77.5,
            77.5,
            77.5,
            77.5,
            77.5,
            76.5,
            76.5,
            76.5,
            76.5,
            76.5,
            76.5,
            76.5,
            75.5,
            75.5,
            75.5,
            75.5,
            75.5,
            75.5,
            75.5
          ],
          "range": "Sheet6!$C$4:$C$430",
          "color": "#08599C"
        },
        {
          "name": "钴计价系数",
          "values": [
            77.5,
            77.5,
            78.0,
            78.0,
            78.5,
            79.0,
            79.0,
            79.0,
            79.0,
            79.0,
            80.0,
            80.0,
            80.0,
            80.0,
            80.0,
            80.0,
            79.0,
            79.0,
            79.0,
            79.0,
            79.0,
            79.0,
            79.0,
            79.0,
            79.0,
            78.5,
            78.5,
            78.5,
            78.5,
            78.5,
            78.5,
            78.5,
            78.5,
            78.5,
            78.5,
            78.5,
            78.5,
            78.5,
            78.5,
            78.0,
            77.0,
            77.0,
            77.0,
            77.0,
            77.0,
            77.0,
            77.0,
            77.0,
            77.0,
            77.0,
            77.0,
            77.0,
            77.5,
            77.5,
            77.5,
            77.5,
            77.5,
            77.0,
            77.0,
            77.0,
            77.0,
            77.0,
            77.0,
            77.0,
            77.0,
            77.0,
            77.0,
            77.0,
            77.0,
            77.0,
            77.0,
            77.0,
            77.0,
            77.0,
            77.0,
            77.0,
            77.0,
            77.0,
            77.0,
            77.0,
            78.0,
            78.0,
            78.0,
            78.0,
            78.0,
            78.0,
            78.0,
            78.0,
            78.0,
            77.5,
            77.5,
            77.5,
            77.5,
            77.5,
            77.5,
            77.5,
            77.5,
            77.0,
            77.0,
            77.5,
            77.0,
            77.0,
            77.0,
            76.0,
            76.0,
            76.0,
            76.0,
            76.5,
            76.5,
            76.5,
            76.5,
            76.5,
            76.5,
            76.5,
            76.5,
            76.5,
            76.5,
            76.5,
            76.5,
            76.5,
            76.5,
            76.5,
            76.5,
            76.5,
            76.5,
            76.5,
            76.0,
            76.0,
            76.0,
            76.0,
            76.0,
            76.0,
            76.0,
            76.0,
            76.0,
            76.0,
            76.0,
            76.0,
            74.0,
            74.0,
            73.5,
            73.5,
            72.5,
            72.5,
            71.5,
            71.0,
            70.5,
            70.0,
            70.0,
            69.0,
            68.0,
            67.0,
            67.0,
            67.0,
            67.0,
            67.0,
            67.0,
            67.0,
            67.0,
            67.0,
            67.0,
            67.0,
            67.0,
            67.0,
            67.0,
            67.0,
            67.0,
            67.0,
            67.0,
            67.0,
            67.0,
            67.0,
            67.0,
            67.0,
            67.0,
            67.0,
            67.0,
            67.0,
            67.0,
            67.0,
            67.0,
            67.0,
            67.0,
            67.0,
            67.0,
            67.0,
            67.0,
            67.0,
            67.0,
            67.0,
            67.0,
            67.0,
            67.0,
            67.0,
            67.0,
            67.0,
            67.0,
            67.0,
            67.0,
            67.0,
            67.0,
            67.0,
            67.0,
            67.0,
            67.0,
            67.0,
            67.0,
            67.0,
            67.0,
            67.0,
            67.0,
            67.0,
            67.0,
            67.0,
            67.0,
            67.0,
            67.0,
            67.0,
            66.5,
            66.5,
            66.5,
            66.5,
            66.5,
            66.5,
            66.5,
            66.5,
            66.5,
            66.5,
            66.5,
            66.5,
            66.5,
            66.5,
            66.5,
            66.5,
            66.5,
            66.5,
            66.5,
            66.5,
            66.5,
            66.5,
            66.5,
            66.5,
            66.5,
            66.5,
            66.5,
            66.5,
            66.5,
            66.5,
            66.5,
            66.5,
            66.5,
            66.5,
            66.5,
            67.0,
            67.0,
            67.0,
            67.0,
            67.0,
            67.0,
            67.0,
            67.0,
            67.0,
            67.0,
            67.0,
            67.0,
            67.0,
            67.0,
            67.0,
            67.0,
            67.5,
            68.0,
            68.0,
            68.0,
            68.0,
            68.0,
            68.0,
            68.0,
            68.0,
            68.5,
            68.5,
            68.5,
            68.5,
            68.5,
            68.5,
            68.5,
            68.5,
            68.5,
            68.5,
            68.5,
            68.5,
            68.5,
            69.0,
            69.0,
            69.0,
            69.0,
            69.0,
            69.0,
            69.0,
            69.0,
            69.0,
            69.0,
            69.0,
            69.0,
            69.0,
            69.0,
            69.0,
            69.0,
            69.0,
            69.0,
            69.0,
            69.5,
            69.5,
            69.5,
            69.5,
            70.0,
            70.0,
            70.0,
            70.0,
            70.0,
            70.0,
            70.0,
            70.5,
            70.5,
            70.5,
            70.5,
            70.5,
            70.5,
            70.5,
            70.5,
            70.5,
            70.5,
            70.5,
            70.5,
            70.5,
            70.5,
            70.5,
            70.5,
            70.5,
            70.5,
            70.5,
            70.5,
            70.5,
            70.5,
            70.5,
            70.5,
            70.5,
            70.5,
            70.5,
            70.5,
            70.5,
            70.5,
            70.5,
            70.5,
            70.5,
            70.5,
            71.0,
            71.0,
            71.0,
            71.0,
            71.0,
            71.0,
            71.0,
            71.0,
            71.0,
            71.0,
            71.0,
            71.0,
            71.0,
            71.0,
            71.0,
            71.0,
            71.5,
            71.5,
            71.5,
            71.5,
            71.5,
            71.5,
            71.5,
            71.5,
            71.5,
            71.5,
            71.5,
            71.5,
            71.5,
            71.5,
            71.5,
            71.5,
            71.5,
            71.5,
            71.5,
            71.5,
            71.5,
            71.5,
            71.5,
            71.5,
            71.5,
            71.5,
            71.0,
            71.0,
            70.5,
            70.5,
            70.5,
            70.5,
            70.5,
            70.5,
            70.5,
            70.5,
            70.5,
            70.5,
            70.5,
            70.5,
            70.5,
            69.5,
            69.5,
            69.5,
            69.5,
            69.5,
            69.5,
            69.5,
            69.5,
            69.5,
            69.5,
            69.5,
            69.5,
            69.5,
            69.5,
            69.5
          ],
          "range": "Sheet6!$D$4:$D$430",
          "color": "#EF0808"
        }
      ],
      "notes": [],
      "hasDateAxis": true,
      "valueRange": {
        "dataMin": 66.5,
        "dataMax": 85.5,
        "suggestedMin": 66,
        "suggestedMax": 87
      }
    },
    {
      "chartPath": "ppt/charts/chart20.xml",
      "chartType": "barChart",
      "title": null,
      "workbook": "ppt/embeddings/Microsoft_Excel_Worksheet19.xlsx",
      "categoryLabels": [
        "2025-10-13",
        "2025-10-10",
        "2025-10-09",
        "2025-09-30",
        "2025-09-29",
        "2025-09-26",
        "2025-09-25",
        "2025-09-24",
        "2025-09-23",
        "2025-09-22",
        "2025-09-19",
        "2025-09-18",
        "2025-09-17",
        "2025-09-16",
        "2025-09-15",
        "2025-09-12",
        "2025-09-11",
        "2025-09-10",
        "2025-09-09",
        "2025-09-08",
        "2025-09-05",
        "2025-09-04",
        "2025-09-03",
        "2025-09-02",
        "2025-09-01",
        "2025-08-29",
        "2025-08-28",
        "2025-08-27",
        "2025-08-26",
        "2025-08-25",
        "2025-08-22",
        "2025-08-21",
        "2025-08-20",
        "2025-08-19",
        "2025-08-18",
        "2025-08-15",
        "2025-08-14",
        "2025-08-13",
        "2025-08-12",
        "2025-08-11",
        "2025-08-08",
        "2025-08-07",
        "2025-08-06",
        "2025-08-05",
        "2025-08-04",
        "2025-08-01",
        "2025-07-31",
        "2025-07-30",
        "2025-07-29",
        "2025-07-28",
        "2025-07-25",
        "2025-07-24",
        "2025-07-23",
        "2025-07-22",
        "2025-07-21",
        "2025-07-18",
        "2025-07-17",
        "2025-07-16",
        "2025-07-15",
        "2025-07-14",
        "2025-07-11",
        "2025-07-10",
        "2025-07-09",
        "2025-07-08",
        "2025-07-07",
        "2025-07-04",
        "2025-07-03",
        "2025-07-02",
        "2025-07-01",
        "2025-06-30",
        "2025-06-27",
        "2025-06-26",
        "2025-06-25",
        "2025-06-24",
        "2025-06-23",
        "2025-06-20",
        "2025-06-19",
        "2025-06-18",
        "2025-06-17",
        "2025-06-16",
        "2025-06-13",
        "2025-06-12",
        "2025-06-11",
        "2025-06-10",
        "2025-06-09",
        "2025-06-06",
        "2025-06-05",
        "2025-06-04",
        "2025-06-03",
        "2025-05-30",
        "2025-05-29",
        "2025-05-28",
        "2025-05-27",
        "2025-05-26",
        "2025-05-23",
        "2025-05-22",
        "2025-05-21",
        "2025-05-20",
        "2025-05-19",
        "2025-05-16",
        "2025-05-15",
        "2025-05-14",
        "2025-05-13",
        "2025-05-12",
        "2025-05-09",
        "2025-05-08",
        "2025-05-07",
        "2025-05-06",
        "2025-04-30",
        "2025-04-29",
        "2025-04-28",
        "2025-04-25",
        "2025-04-24",
        "2025-04-23",
        "2025-04-22",
        "2025-04-21",
        "2025-04-18",
        "2025-04-17",
        "2025-04-16",
        "2025-04-15",
        "2025-04-14",
        "2025-04-11",
        "2025-04-10",
        "2025-04-09",
        "2025-04-08",
        "2025-04-07",
        "2025-04-03",
        "2025-04-02",
        "2025-04-01",
        "2025-03-31",
        "2025-03-28",
        "2025-03-27",
        "2025-03-26",
        "2025-03-25",
        "2025-03-24",
        "2025-03-21",
        "2025-03-20",
        "2025-03-19",
        "2025-03-18",
        "2025-03-17",
        "2025-03-14",
        "2025-03-13",
        "2025-03-12",
        "2025-03-11",
        "2025-03-10",
        "2025-03-07",
        "2025-03-06",
        "2025-03-05",
        "2025-03-04",
        "2025-03-03",
        "2025-02-28",
        "2025-02-27",
        "2025-02-26",
        "2025-02-25",
        "2025-02-24",
        "2025-02-21",
        "2025-02-20",
        "2025-02-19",
        "2025-02-18",
        "2025-02-17",
        "2025-02-14",
        "2025-02-13",
        "2025-02-12",
        "2025-02-11",
        "2025-02-10",
        "2025-02-07",
        "2025-02-06",
        "2025-02-05",
        "2025-01-27",
        "2025-01-24",
        "2025-01-23",
        "2025-01-22",
        "2025-01-21",
        "2025-01-20",
        "2025-01-17",
        "2025-01-16",
        "2025-01-15",
        "2025-01-14",
        "2025-01-13",
        "2025-01-10",
        "2025-01-09",
        "2025-01-08",
        "2025-01-07",
        "2025-01-06",
        "2025-01-03",
        "2025-01-02",
        "2024-12-31",
        "2024-12-30",
        "2024-12-27",
        "2024-12-26",
        "2024-12-25",
        "2024-12-24",
        "2024-12-23",
        "2024-12-20",
        "2024-12-19",
        "2024-12-18",
        "2024-12-17",
        "2024-12-16",
        "2024-12-13",
        "2024-12-12",
        "2024-12-11",
        "2024-12-10",
        "2024-12-09",
        "2024-12-06",
        "2024-12-05",
        "2024-12-04",
        "2024-12-03",
        "2024-12-02",
        "2024-11-29",
        "2024-11-28",
        "2024-11-27",
        "2024-11-26",
        "2024-11-25",
        "2024-11-22",
        "2024-11-21",
        "2024-11-20",
        "2024-11-19",
        "2024-11-18",
        "2024-11-15",
        "2024-11-14",
        "2024-11-13",
        "2024-11-12",
        "2024-11-11",
        "2024-11-08",
        "2024-11-07",
        "2024-11-06",
        "2024-11-05",
        "2024-11-04",
        "2024-11-01",
        "2024-10-31",
        "2024-10-30",
        "2024-10-29",
        "2024-10-28",
        "2024-10-25",
        "2024-10-24",
        "2024-10-23",
        "2024-10-22",
        "2024-10-21",
        "2024-10-18",
        "2024-10-17",
        "2024-10-16",
        "2024-10-15",
        "2024-10-14",
        "2024-10-11",
        "2024-10-10",
        "2024-10-09",
        "2024-10-08",
        "2024-09-30",
        "2024-09-27",
        "2024-09-26",
        "2024-09-25",
        "2024-09-24",
        "2024-09-23",
        "2024-09-20",
        "2024-09-19",
        "2024-09-18",
        "2024-09-13",
        "2024-09-12",
        "2024-09-11",
        "2024-09-10",
        "2024-09-09",
        "2024-09-06",
        "2024-09-05",
        "2024-09-04",
        "2024-09-03",
        "2024-09-02",
        "2024-08-30",
        "2024-08-29",
        "2024-08-28",
        "2024-08-27",
        "2024-08-26",
        "2024-08-23",
        "2024-08-22",
        "2024-08-21",
        "2024-08-20",
        "2024-08-19",
        "2024-08-16",
        "2024-08-15",
        "2024-08-14",
        "2024-08-13",
        "2024-08-12",
        "2024-08-09",
        "2024-08-08",
        "2024-08-07",
        "2024-08-06",
        "2024-08-05",
        "2024-08-02",
        "2024-08-01",
        "2024-07-31",
        "2024-07-30",
        "2024-07-29",
        "2024-07-26",
        "2024-07-25",
        "2024-07-24",
        "2024-07-23",
        "2024-07-22",
        "2024-07-19",
        "2024-07-18",
        "2024-07-17",
        "2024-07-16",
        "2024-07-15",
        "2024-07-12",
        "2024-07-11",
        "2024-07-10",
        "2024-07-09",
        "2024-07-08",
        "2024-07-05",
        "2024-07-04",
        "2024-07-03",
        "2024-07-02",
        "2024-07-01",
        "2024-06-28",
        "2024-06-27",
        "2024-06-26",
        "2024-06-25",
        "2024-06-24",
        "2024-06-21",
        "2024-06-20",
        "2024-06-19",
        "2024-06-18",
        "2024-06-17",
        "2024-06-14",
        "2024-06-13",
        "2024-06-12",
        "2024-06-11",
        "2024-06-07",
        "2024-06-06",
        "2024-06-05",
        "2024-06-04",
        "2024-06-03",
        "2024-05-31",
        "2024-05-30",
        "2024-05-29",
        "2024-05-28",
        "2024-05-27",
        "2024-05-24",
        "2024-05-23",
        "2024-05-22",
        "2024-05-21",
        "2024-05-20",
        "2024-05-17",
        "2024-05-16",
        "2024-05-15",
        "2024-05-14",
        "2024-05-13",
        "2024-05-10",
        "2024-05-09",
        "2024-05-08",
        "2024-05-07",
        "2024-05-06",
        "2024-04-30",
        "2024-04-29",
        "2024-04-26",
        "2024-04-25",
        "2024-04-24",
        "2024-04-23",
        "2024-04-22",
        "2024-04-19",
        "2024-04-18",
        "2024-04-17",
        "2024-04-16",
        "2024-04-15",
        "2024-04-12",
        "2024-04-11",
        "2024-04-10",
        "2024-04-09",
        "2024-04-08",
        "2024-04-03",
        "2024-04-02",
        "2024-04-01",
        "2024-03-29",
        "2024-03-28",
        "2024-03-27",
        "2024-03-26",
        "2024-03-25",
        "2024-03-22",
        "2024-03-21",
        "2024-03-20",
        "2024-03-19",
        "2024-03-18",
        "2024-03-15",
        "2024-03-14",
        "2024-03-13",
        "2024-03-12",
        "2024-03-11",
        "2024-03-08",
        "2024-03-07",
        "2024-03-06",
        "2024-03-05",
        "2024-03-04",
        "2024-03-01",
        "2024-02-29",
        "2024-02-28",
        "2024-02-27",
        "2024-02-26",
        "2024-02-23",
        "2024-02-22",
        "2024-02-21",
        "2024-02-20",
        "2024-02-19",
        "2024-02-08",
        "2024-02-07",
        "2024-02-06",
        "2024-02-05",
        "2024-02-02",
        "2024-02-01",
        "2024-01-31",
        "2024-01-30",
        "2024-01-29",
        "2024-01-26",
        "2024-01-25",
        "2024-01-24",
        "2024-01-23",
        "2024-01-22",
        "2024-01-19",
        "2024-01-18",
        "2024-01-17",
        "2024-01-16",
        "2024-01-15",
        "2024-01-12",
        "2024-01-11",
        "2024-01-10",
        "2024-01-09",
        "2024-01-08",
        "2024-01-05",
        "2024-01-04",
        "2024-01-03",
        "2024-01-02"
      ],
      "categoryRange": "Sheet7!$B$4:$B$431",
      "series": [
        {
          "name": "硫酸镍与金属镍价差",
          "values": [
            7790.909090909088,
            5977.272727272721,
            5954.545454545456,
            7154.545454545456,
            7554.545454545456,
            6881.8181818181765,
            5231.8181818181765,
            6604.545454545456,
            7104.545454545456,
            6354.545454545456,
            6168.1818181818235,
            5936.363636363632,
            5704.545454545456,
            4904.545454545456,
            5372.727272727279,
            5290.909090909088,
            6418.1818181818235,
            6318.1818181818235,
            5968.1818181818235,
            5181.8181818181765,
            5981.8181818181765,
            5631.8181818181765,
            5181.8181818181765,
            3450.0,
            3063.6363636363676,
            4786.363636363632,
            5259.090909090912,
            3681.8181818181765,
            5386.363636363632,
            5586.363636363632,
            6195.454545454544,
            5595.454545454544,
            5700.0,
            4809.090909090912,
            4668.1818181818235,
            4704.545454545456,
            2736.3636363636324,
            2286.3636363636324,
            2545.454545454544,
            2922.7272727272793,
            3827.2727272727207,
            3627.2727272727207,
            3495.454545454544,
            3695.454545454544,
            4254.545454545456,
            4759.090909090912,
            4159.090909090912,
            2309.0909090909117,
            2959.0909090909117,
            2118.1818181818235,
            250.0,
            109.09090909091174,
            713.6363636363676,
            1213.6363636363676,
            1872.7272727272793,
            3222.7272727272793,
            4227.272727272721,
            2527.2727272727207,
            4277.272727272721,
            3786.3636363636324,
            3386.3636363636324,
            4986.363636363632,
            5386.363636363632,
            4390.909090909088,
            3540.9090909090883,
            2090.9090909090883,
            3045.454545454544,
            3645.454545454544,
            4295.454545454544,
            3620.454545454544,
            3645.454545454544,
            4345.454545454544,
            6495.454545454544,
            7045.454545454544,
            6445.454545454544,
            5220.454545454544,
            6361.363636363632,
            6997.727272727279,
            7452.272727272721,
            6956.8181818181765,
            6081.8181818181765,
            5731.8181818181765,
            4881.8181818181765,
            4781.8181818181765,
            3681.8181818181765,
            4181.8181818181765,
            4531.8181818181765,
            4661.363636363632,
            5236.363636363632,
            5961.363636363632,
            6761.363636363632,
            5090.909090909088,
            5040.909090909088,
            4190.909090909088,
            4115.909090909088,
            3790.9090909090883,
            3765.9090909090883,
            3725.0,
            3250.0,
            2025.0,
            1875.0,
            2720.454545454544,
            3845.454545454544,
            1570.4545454545441,
            4020.454545454544,
            4095.454545454544,
            3270.454545454544,
            3284.0909090909117,
            3561.3636363636324,
            3036.3636363636324,
            3786.3636363636324,
            2061.3636363636324,
            1836.3636363636324,
            1775.0,
            1900.0,
            1800.0,
            1400.0,
            1225.0,
            2595.454545454544,
            3850.0,
            5077.272727272721,
            7677.272727272721,
            7652.272727272721,
            8952.27272727272,
            8909.090909090912,
            7609.090909090912,
            759.0909090909117,
            -422.72727272727934,
            -745.4545454545441,
            -1695.4545454545441,
            -2695.454545454544,
            -1445.4545454545441,
            -1606.8181818181765,
            -531.8181818181765,
            -925.0,
            -1781.8181818181765,
            -722.7272727272793,
            -2397.7272727272793,
            -2297.7272727272793,
            -5300.0,
            -7006.8181818181765,
            -6234.090909090912,
            -6009.090909090912,
            -6213.636363636368,
            -6727.272727272721,
            -4879.545454545456,
            -4563.636363636368,
            -4027.2727272727207,
            -4409.090909090912,
            -4197.727272727279,
            -4300.0,
            -3154.545454545456,
            -2495.454545454544,
            -2520.454545454544,
            -3100.0,
            -3650.0,
            -2525.0,
            -2425.0,
            -2225.0,
            -1954.5454545454559,
            -2904.545454545456,
            -2854.545454545456,
            -2899.545454545456,
            -3304.545454545456,
            -5179.545454545456,
            -5904.545454545456,
            -3995.454545454544,
            -2140.9090909090883,
            -2390.9090909090883,
            -1890.9090909090883,
            -3090.9090909090883,
            -5886.363636363632,
            -7047.727272727279,
            -6363.636363636368,
            -7029.545454545456,
            -6620.454545454544,
            -6972.727272727279,
            -7420.454545454544,
            -6995.454545454544,
            -5220.454545454544,
            -4940.909090909088,
            -4886.363636363632,
            -2706.8181818181765,
            -2827.2727272727207,
            -2302.2727272727207,
            -4202.272727272721,
            -3952.2727272727207,
            -4127.272727272721,
            -5577.272727272721,
            -5352.272727272721,
            -5177.272727272721,
            -3922.7272727272793,
            -4372.727272727279,
            -2157.7272727272793,
            -2672.7272727272793,
            -3847.7272727272793,
            -5413.636363636368,
            -6224.545454545456,
            -8779.545454545456,
            -7475.0,
            -5100.0,
            -6859.090909090912,
            -7109.090909090912,
            -5450.0,
            -6302.272727272721,
            -7934.090909090912,
            -4775.0,
            -5263.636363636368,
            -7311.363636363632,
            -6336.363636363632,
            -5536.363636363632,
            -7777.272727272721,
            -7663.636363636368,
            -5754.545454545456,
            -7654.545454545456,
            -5895.454545454544,
            -4065.9090909090883,
            -2563.6363636363676,
            -1922.7272727272793,
            -2213.6363636363676,
            -2981.8181818181765,
            -4504.545454545456,
            -4540.909090909088,
            -5661.363636363632,
            -2522.7272727272793,
            -1740.9090909090883,
            268.1818181818235,
            18.181818181823473,
            1168.1818181818235,
            643.1818181818235,
            336.3636363636324,
            581.8181818181765,
            -1263.6363636363676,
            -1186.3636363636324,
            -759.0909090909117,
            -756.8181818181765,
            318.1818181818235,
            -1022.7272727272793,
            -390.90909090908826,
            -5045.454545454544,
            -4505.454545454544,
            -5745.454545454544,
            -6106.8181818181765,
            -5981.8181818181765,
            -4618.1818181818235,
            -6886.363636363632,
            -7731.8181818181765,
            -4081.8181818181765,
            -1152.2727272727207,
            -1386.3636363636324,
            -961.3636363636324,
            1338.6363636363676,
            2113.6363636363676,
            1488.6363636363676,
            2809.0909090909117,
            3206.8181818181765,
            3177.2727272727207,
            3327.2727272727207,
            6022.727272727279,
            6300.0,
            5331.8181818181765,
            4172.727272727279,
            3247.7272727272793,
            2472.7272727272793,
            -677.2727272727207,
            531.8181818181765,
            -3254.545454545456,
            -3195.454545454544,
            -4050.0,
            -4502.272727272721,
            -3454.545454545456,
            -2531.8181818181765,
            -2870.454545454544,
            -3984.0909090909117,
            -3211.3636363636324,
            -3250.0,
            -2863.6363636363676,
            -1888.6363636363676,
            -2213.6363636363676,
            -2450.0,
            -1700.0,
            -4286.363636363632,
            -1181.8181818181765,
            -3350.0,
            -3068.1818181818235,
            -3713.6363636363676,
            -4213.636363636368,
            -6136.363636363632,
            -5086.363636363632,
            809.0909090909117,
            1309.0909090909117,
            2209.0909090909117,
            4645.454545454544,
            1145.4545454545441,
            745.4545454545441,
            895.4545454545441,
            -704.5454545454559,
            -704.5454545454559,
            -3304.545454545456,
            -4104.545454545456,
            -5054.545454545456,
            -3354.545454545456,
            -4054.545454545456,
            -5104.545454545456,
            -7904.545454545456,
            -8154.545454545456,
            -6654.545454545456,
            -8404.545454545456,
            -7004.545454545456,
            -7554.545454545456,
            -6904.545454545456,
            -5854.545454545456,
            -5954.545454545456,
            -3518.1818181818235,
            -2831.8181818181765,
            -945.4545454545587,
            -47.72727272726479,
            2075.0,
            5218.1818181818235,
            5309.090909090912,
            5295.454545454559,
            6513.636363636353,
            7254.545454545441,
            6945.454545454559,
            8809.090909090912,
            6690.909090909088,
            7927.272727272735,
            7431.8181818181765,
            4636.363636363647,
            1936.363636363647,
            886.363636363647,
            -1913.636363636353,
            -3363.636363636353,
            -4700.0,
            -3336.363636363647,
            -2822.727272727265,
            -4181.8181818181765,
            -10263.636363636353,
            -9995.454545454559,
            -10913.636363636353,
            -7154.545454545441,
            -3536.363636363647,
            -1513.636363636353,
            -1518.1818181818235,
            -768.1818181818235,
            -1252.2727272727352,
            -177.2727272727352,
            -427.2727272727352,
            -2927.272727272735,
            -2354.5454545454413,
            -2881.8181818181765,
            -2286.363636363647,
            -2690.9090909090883,
            -2595.4545454545587,
            -1872.7272727272648,
            -2972.727272727265,
            -7122.727272727265,
            -622.7272727272648,
            1802.2727272727352,
            4254.545454545441,
            3354.5454545454413,
            204.54545454544132,
            1754.5454545454413,
            81.81818181817653,
            -18.181818181823473,
            3736.363636363647,
            3536.363636363647,
            6340.909090909088,
            8722.727272727265,
            11322.727272727265,
            10722.727272727265,
            11572.727272727265,
            11422.727272727265,
            9272.727272727265,
            7047.727272727265,
            6772.727272727265,
            3668.1818181818235,
            3836.363636363647,
            300.0,
            -2309.0909090909117,
            -2943.1818181818235,
            -4722.727272727265,
            -4656.8181818181765,
            -4711.363636363647,
            -2090.9090909090883,
            -1915.9090909090883,
            -770.4545454545587,
            -152.2727272727352,
            -3836.363636363647,
            -5186.363636363647,
            -5618.1818181818235,
            -5650.0,
            -4609.090909090912,
            -2765.9090909090883,
            -4440.909090909088,
            -7677.272727272721,
            -2359.0909090909117,
            -188.6363636363676,
            -88.6363636363676,
            -904.5454545454559,
            -1113.6363636363676,
            436.3636363636324,
            336.3636363636324,
            -868.1818181818235,
            -2972.7272727272793,
            -3477.2727272727207,
            -4581.8181818181765,
            -5081.8181818181765,
            -6836.363636363632,
            -8740.909090909088,
            -7390.909090909088,
            -7290.909090909088,
            -6795.454545454544,
            -4995.454545454544,
            -7095.454545454544,
            -6550.0,
            -6400.0,
            -5650.0,
            -5900.0,
            -7975.0,
            -6825.0,
            -4200.0,
            -4400.0,
            -3375.0,
            -2900.0,
            -4050.0,
            -7300.0,
            -5700.0
          ],
          "range": "Sheet7!$F$4:$F$431",
          "color": "#52596B"
        }
      ],
      "notes": [],
      "hasDateAxis": true,
      "valueRange": {
        "dataMin": -10913.636364,
        "dataMax": 11572.727273,
        "suggestedMin": -11000,
        "suggestedMax": 13000
      }
    }
  ]
}